matrixutils/__init__.py
matrixutils/codeutils.py
matrixutils/coordutils.py
matrixutils/curvutils.py
matrixutils/interputils.py
matrixutils/interputils_cython.so
matrixutils/matutils.py
matrixutils/meshutils.py
matrixutils/setup.py
matrixutils-0.0.1.dist-info/DESCRIPTION.rst
matrixutils-0.0.1.dist-info/METADATA
matrixutils-0.0.1.dist-info/RECORD
matrixutils-0.0.1.dist-info/WHEEL
matrixutils-0.0.1.dist-info/metadata.json
matrixutils-0.0.1.dist-info/top_level.txt
