Metadata-Version: 2.0
Name: matrixutils
Version: 0.0.1
Summary: utilities for working with matrices as linear operators in python
Home-page: http://simpeg.xyz/
Author: OpenGeophysics Developers
Author-email: admin@simpeg.xyz
License: MIT
Download-URL: https://github.com/OpenGeophysics/matrixutils
Keywords: finite volume,discretization,pde,ode
Platform: Windows
Platform: Linux
Platform: Solaris
Platform: Mac OS-X
Platform: Unix
Classifier: Development Status :: 4 - Beta
Classifier: Intended Audience :: Developers
Classifier: Intended Audience :: Science/Research
Classifier: License :: OSI Approved :: MIT License
Classifier: Programming Language :: Python
Classifier: Topic :: Scientific/Engineering
Classifier: Topic :: Scientific/Engineering :: Mathematics
Classifier: Topic :: Scientific/Engineering :: Physics
Classifier: Operating System :: Microsoft :: Windows
Classifier: Operating System :: POSIX
Classifier: Operating System :: Unix
Classifier: Operating System :: MacOS
Classifier: Natural Language :: English
Requires-Dist: cython
Requires-Dist: matplotlib
Requires-Dist: numpy (>=1.7)
Requires-Dist: properties (>=0.3.6b0)
Requires-Dist: scipy (>=0.13)
